WhitelistTMTBot/__init__.py
WhitelistTMTBot/dataclass.py
WhitelistTMTBot/dbase.py
WhitelistTMTBot/main.py
WhitelistTMTBot/server.py
WhitelistTMTBot-0.3.10.dist-info/METADATA
WhitelistTMTBot-0.3.10.dist-info/WHEEL
WhitelistTMTBot-0.3.10.dist-info/top_level.txt
WhitelistTMTBot-0.3.10.dist-info/RECORD
