Metadata-Version: 2.1
Name: WhitelistTMTBot
Version: 0.3.10
Summary: This is the simplest module for quick work with telegram bots.
Home-page: https://gitlab.com/nmModi/whitelist_tmt_bot.git
Author: nmmodi
Author-email: mniyazkhanov@gmail.com
License: UNKNOWN
Keywords: telegram bot
Platform: UNKNOWN
Classifier: Programming Language :: Python :: 3.10
Classifier: License :: OSI Approved :: MIT License
Classifier: Operating System :: OS Independent
Requires-Python: >=3.6
Requires-Dist: requests (==2.31.0)
